SesamJackTop/__init__.py
SesamJackTop/sesam.py
SesamJackTop/Excel/__init__.py
SesamJackTop/Excel/points.py
SesamJackTop-0.0.10.dist-info/LICENSE.txt
SesamJackTop-0.0.10.dist-info/METADATA
SesamJackTop-0.0.10.dist-info/WHEEL
SesamJackTop-0.0.10.dist-info/top_level.txt
SesamJackTop-0.0.10.dist-info/RECORD
