Metadata-Version: 2.1
Name: SesamJackTop
Version: 0.0.10
Summary: A Sesam GeniE utility package
Author-email: Abin Pulivelil <abinpulivelil@gmail.com>
Classifier: Programming Language :: Python :: 3
Classifier: License :: OSI Approved :: MIT License
Classifier: Operating System :: OS Independent
Requires-Python: >=3.7
License-File: LICENSE.txt
